{
    "minItems": 1,
    "items": {
        "minItems": 4,
        "items": [
            {
                "type": "integer",
                "minimum": 1
            },
            {
                "type": "string"
            },
            {
                "type": "string"
            },
            {
                "items": {
                    "type": "number",
                    "minimum": 0
                },
                "maxItems": 3,
                "minItems": 3,
                "type": "array",
                "additionalItems": false
            },
            {
                "items": {
                    "type": "number"
                },
                "maxItems": 3,
                "minItems": 3,
                "type": "array",
                "additionalItems": false
            },
            {
                "type": "string"
            }
        ],
        "type": "array",
        "additionalItems": false
    },
    "type": "array",
    "additionalItems": false
}